cn/__init__.py
cn/mldn/__init__.py
cn/mldn/info/__init__.py
cn/mldn/info/information.py
cn/mldn/info/mess.py
cn/mldn/info/message.py
yootk_mess-1.5.dist-info/METADATA
yootk_mess-1.5.dist-info/WHEEL
yootk_mess-1.5.dist-info/top_level.txt
yootk_mess-1.5.dist-info/RECORD
