Metadata-Version: 2.1
Name: yootk-mess
Version: 1.5
Summary: Get Yootk Information.
Home-page: http://www.yootk.com
Author: 李兴华
Author-email: UNKNOWN
License: UNKNOWN
Platform: UNKNOWN
